Metadata-Version: 2.1
Name: odoo10-addon-users-ldap-groups
Version: 10.0.0.0.1
Summary: Adds user accounts to groups based on rules defined by the administrator.
Home-page: UNKNOWN
Author: Therp BV, Odoo Community Association (OCA)
Author-email: support@odoo-community.org
License: AGPL-3
Platform: UNKNOWN
Classifier: Programming Language :: Python
Classifier: Framework :: Odoo
Classifier: License :: OSI Approved :: GNU Affero General Public License v3
Requires-Python: ~=2.7
Requires-Dist: odoo (<10.1dev,>=10.0)
Requires-Dist: python-ldap
